{
  "id": "d643f0ec-4a6a-44e8-903d-f5f9a9430a1b",
  "duration": 0.20000000298023224,
  "loopMode": "once",
  "tracks": [
    {
      "propertyPath": "Sprite2D.sprite",
      "keyframes": [
        {
          "time": 0,
          "value": {
            "spriteId": "sprite-mjtc09zo-0",
            "textureGuid": "character-stop-run-mjtal8oq"
          }
        },
        {
          "time": 0.5,
          "value": {
            "spriteId": "sprite-mjtc09zo-1",
            "textureGuid": "character-stop-run-mjtal8oq"
          }
        }
      ],
      "interpolationMode": "discrete"
    }
  ],
  "name": "Character Stop Run"
}